arena_engine/__init__.py
arena_engine/admin.py
arena_engine/apps.py
arena_engine/models.py
arena_engine/tests.py
arena_engine/views.py
arena_engine/migrations/__init__.py
tests/__init__.py
tests/asgi.py
tests/settings.py
tests/urls.py
tests/wsgi.py
arena_engine-0.0.1.dist-info/LICENSE
arena_engine-0.0.1.dist-info/METADATA
arena_engine-0.0.1.dist-info/WHEEL
arena_engine-0.0.1.dist-info/top_level.txt
arena_engine-0.0.1.dist-info/RECORD
