Metadata-Version: 2.1
Name: arena-engine
Version: 0.0.1
Summary: An Arena Engine
Home-page: https://github.com/lladdy/arena-engine
Author: lladdy
Author-email: me@lladdy.com
License: UNKNOWN
Platform: UNKNOWN
Classifier: Programming Language :: Python :: 3
Classifier: License :: OSI Approved :: GNU General Public License v3 (GPLv3)
Classifier: Operating System :: OS Independent
Requires-Python: >=3.7
